tribun/__init__.py
tribun/consul.py
tribun/errors.py
tribun/key.py
tribun/main.py
tribun/operations.py
tribun/revision.py
tribun-0.9.dist-info/METADATA
tribun-0.9.dist-info/WHEEL
tribun-0.9.dist-info/entry_points.txt
tribun-0.9.dist-info/top_level.txt
tribun-0.9.dist-info/RECORD
